{
  "filename": "vivek_resume.txt",
  "cleaned_text": "V\nI\nVEK\nV\nA\nISH +91\n-7417378004 Greater Noida vaishvivek634@gmail.com LinkedIn Portfolio\nA\nC\nA\nD\nE\nMIC\nD\nE\nT\nA\nILS B.tech\nCSE AIML, Galgotias University Expected 2026\nC\nGPA: 7\nBRB Model School 2022 Percentage: 85.4\nBRB Model School 2020 Percentage: 75.8\nE\nX\nP\nE\nR\nI\nE\nNCE\nA\nIML\nI\nN\nT\nE\nR\nN\nS\nHIP VIRTUAL October 2024\n- December 2024\nEngineered high\n-precision artificial intelligence models for face recognition and object detection, enhancing accuracy by 15 through advanced deep learning techniques.\nT\nE\nC\nH\nN\nI\nCAL\nS\nK\nI\nLLS\nProgramming Languages: Python, Javascript, Typescript, Java, C, C++\nWeb Technologies: React.js, Next.js, Tailwind\nCSS\nBackend Technologies: Node.js, Express.js, Firebase\nTools: Git, Postman, Docker\nP\nR\nO\nJ\nE\nCTS\nSearch  Ranking Algorithm for User Matching\n- Python, Scikit\n-learn, Pandas January 2025\nDeveloped an advanced rule\n-based ranking system to dynamically sort and prioritize search results based on experience, rating, and user preferences.\nImplemented multi\n-criteria filtering that allows users to search by name, location, and multiple skills, sup\n- porting flexible and precise queries.\nDesigned a dynamic sorting algorithm enabling users to rank search results by experience, rating, or both simultaneously, improving result relevance.\nOptimized query performance for large datasets, ensuring real\n-time search and sorting with minimal latency.\nAutobook\n- Typescript, Google Firebase, Shadcn/UI, Tailwind\nCSS July 2024\nDeveloped a dynamic note\n-taking application using React.js and Redux for an interactive and state\n-managed frontend, enhancing user productivity.\nEngineered a secure and scalable backend using Firebase, integrating Firestore for real\n-time data storage and Firebase Storage for efficient file management.\nIntegrated a third\n-party email service to automate note generation email notifications, improving user en\n- gagement and communication.\nStandardized data structures and application programming interface contracts using TypeScript interfaces, resulting in a 25 decrease in data\n-related bugs.\nA\nC\nH\nI\nE\nV\nE\nM\nE\nNTS\nParticipated  developed an RL\n-based price optimization model in a Code Kshetra 2.0 hackathon, leveraging Q\n-learning and machine learning simulations to maximize sales and conversions.\nCompleted a certified web development course, mastering modern frameworks and tools.",
  "name": "C++\nWeb Technologies",
  "contact_info": {
    "emails": [
      "vaishvivek634@gmail.com"
    ],
    "phones": [
      "+91-7417378004",
      "7417378004"
    ],
    "urls": []
  },
  "sections_found": {
    "education": 3,
    "experience": 13,
    "skills": 18,
    "projects": 23
  },
  "keywords": [
    "user",
    "search",
    "model",
    "firebase",
    "result",
    "experience",
    "typescript",
    "rank",
    "develop",
    "base",
    "sort",
    "aiml",
    "school",
    "percentage",
    "engineer",
    "enhance",
    "advanced",
    "learning",
    "skill",
    "python",
    "technology",
    "tailwindcss",
    "backend",
    "tool",
    "algorithm",
    "rating",
    "query",
    "dynamic",
    "improve",
    "real"
  ],
  "skills": [
    "tool",
    "service",
    "generation",
    "time",
    "shadcn",
    "c++",
    "decrease",
    "system",
    "go",
    "percentage",
    "css",
    "development",
    "git",
    "api",
    "docker",
    "firebase",
    "scala",
    "query",
    "pandas",
    "management",
    "location",
    "deep learning",
    "node.js",
    "rest",
    "structure",
    "scikit-learn",
    "react",
    "r",
    "express",
    "javascript",
    "java",
    "python"
  ]
}